MANIFEST.in
README.rst
setup.cfg
setup.py
lambda_layer/__init__.py
lambda_layer/cli.py
lambda_layer/config.py
lambda_layer/env.py
lambda_layer/version.py
lambda_layer.egg-info/PKG-INFO
lambda_layer.egg-info/SOURCES.txt
lambda_layer.egg-info/dependency_links.txt
lambda_layer.egg-info/entry_points.txt
lambda_layer.egg-info/requires.txt
lambda_layer.egg-info/top_level.txt
lambda_layer/package/__init__.py
lambda_layer/package/bash.py
lambda_layer/package/common.py
lambda_layer/package/main.py