Metadata-Version: 1.2
Name: lambda-layer
Version: 0.0.1
Summary: Create lambda layers for your python dependencies!
Home-page: https://github.com/patdaburu/lambda_layer
Author: Pat Daburu
Author-email: pat@daburu.net
License: MIT
Download-URL: https://github.com/patdaburu/lambda_layer/archive/0.0.1.tar.gz
Platform: UNKNOWN
Classifier: Development Status :: 3 - Alpha
Classifier: Intended Audience :: Developers
Classifier: Topic :: Software Development :: Libraries
Classifier: License :: OSI Approved :: MIT License
Classifier: Programming Language :: Python :: 3.6
Requires-Python: >=0.0.1
